app/__init__.py
app/aiops/__init__.py
app/aiops/agent.py
app/aiops/prompt.py
app/api/ai_operator.py
app/main.py
app/openapi/__init__.py
app/openapi/openapi_handler.py
app/settings.py
app/util/__init__.py
app/util/header_manager.py
app/util/tool_generator.py
ml_ai_ops-0.1.0.dist-info/LICENSE
ml_ai_ops-0.1.0.dist-info/METADATA
ml_ai_ops-0.1.0.dist-info/WHEEL
ml_ai_ops-0.1.0.dist-info/RECORD
