Metadata-Version: 2.1
Name: ml-ai-ops
Version: 0.1.0
Summary: 
Author: Kilsoo Kang
Author-email: kilsoo75@gmail.com
Requires-Python: >=3.12,<4.0
Classifier: Programming Language :: Python :: 3
Classifier: Programming Language :: Python :: 3.12
Classifier: Programming Language :: Python :: 3.13
Requires-Dist: chainlit (>=1.3.2,<2.0.0)
Requires-Dist: colorlog (>=6.9.0,<7.0.0)
Requires-Dist: fastapi (>=0.115.5,<0.116.0)
Requires-Dist: gevent (>=24.11.1,<25.0.0)
Requires-Dist: kubernetes (>=31.0.0,<32.0.0)
Requires-Dist: langchain (>=0.3.8,<0.4.0)
Requires-Dist: langchain-community (>=0.3.8,<0.4.0)
Requires-Dist: langchain-openai (>=0.2.10,<0.3.0)
Requires-Dist: langchain-text-splitters (>=0.3.2,<0.4.0)
Requires-Dist: langgraph (>=0.2.53,<0.3.0)
Requires-Dist: openapi-spec-validator (>=0.7.1,<0.8.0)
Requires-Dist: pandas (>=2.2.3,<3.0.0)
Requires-Dist: pymongo (>=4.10.1,<5.0.0)
Requires-Dist: pypdf (>=5.1.0,<6.0.0)
Requires-Dist: sse-starlette (>=2.1.3,<3.0.0)
Requires-Dist: starlette-csrf (>=3.0.0,<4.0.0)
Requires-Dist: tavily-python (>=0.5.0,<0.6.0)
Requires-Dist: uvicorn (==0.25.0)
Requires-Dist: wikipedia (>=1.4.0,<2.0.0)
